MANIFEST.in
NEWS.rst
README.rst
lookaheadtools.py
setup.py
docs/UserManual.rst
lookaheadtools.egg-info/PKG-INFO
lookaheadtools.egg-info/SOURCES.txt
lookaheadtools.egg-info/dependency_links.txt
lookaheadtools.egg-info/top_level.txt
tests/__init__.py
tests/test_lookaheadtools.py