Metadata-Version: 1.0
Name: lookaheadtools
Version: 0.2b
Summary: Make any iterator a look-ahead iterator. Specialized look-ahead iterators for text files.
Home-page: http://github.com/dbc/lookaheadtools
Author: David B. Curtis
Author-email: davecurtis@sonic.net
License: BSD
Platform: any
